chgksuite/__init__.py
chgksuite/__main__.py
chgksuite/cli.py
chgksuite/common.py
chgksuite/parser.py
chgksuite/parser_db.py
chgksuite/trello.py
chgksuite/typotools.py
chgksuite/version.py
chgksuite/vulture_whitelist.py
chgksuite/composer/__init__.py
chgksuite/composer/chgksuite_parser.py
chgksuite/composer/composer_common.py
chgksuite/composer/db.py
chgksuite/composer/docx.py
chgksuite/composer/latex.py
chgksuite/composer/lj.py
chgksuite/composer/openquiz.py
chgksuite/composer/pptx.py
chgksuite/composer/reddit.py
chgksuite/composer/stats.py
chgksuite/composer/telegram.py
chgksuite/composer/telegram_bot.py
chgksuite/composer/telegram_parser.py
chgksuite/handouter/__init__.py
chgksuite/handouter/gen.py
chgksuite/handouter/installer.py
chgksuite/handouter/pack.py
chgksuite/handouter/runner.py
chgksuite/handouter/tex_internals.py
chgksuite/handouter/utils.py
chgksuite/resources/cheader.tex
chgksuite/resources/fix-unnumbered-sections.sty
chgksuite/resources/labels_by.toml
chgksuite/resources/labels_by_tar.toml
chgksuite/resources/labels_en.toml
chgksuite/resources/labels_kz_cyr.toml
chgksuite/resources/labels_ru.toml
chgksuite/resources/labels_sr.toml
chgksuite/resources/labels_ua.toml
chgksuite/resources/labels_uz.toml
chgksuite/resources/labels_uz_cyr.toml
chgksuite/resources/pptx_config.toml
chgksuite/resources/regexes_by.json
chgksuite/resources/regexes_en.json
chgksuite/resources/regexes_kz_cyr.json
chgksuite/resources/regexes_ru.json
chgksuite/resources/regexes_sr.json
chgksuite/resources/regexes_ua.json
chgksuite/resources/regexes_uz_cyr.json
chgksuite/resources/template.docx
chgksuite/resources/template.pptx
chgksuite/resources/trello.json
chgksuite-0.26.1.dist-info/licenses/LICENSE
chgksuite-0.26.1.dist-info/METADATA
chgksuite-0.26.1.dist-info/WHEEL
chgksuite-0.26.1.dist-info/entry_points.txt
chgksuite-0.26.1.dist-info/top_level.txt
chgksuite-0.26.1.dist-info/RECORD
