Metadata-Version: 2.4
Name: chgksuite
Version: 0.26.1
Summary: A package for chgk automation
Home-page: https://gitlab.com/peczony/chgksuite
Author: Alexander Pecheny
Author-email: ap@pecheny.me
Classifier: Programming Language :: Python :: 3
Classifier: License :: OSI Approved :: MIT License
Classifier: Operating System :: OS Independent
License-File: LICENSE
Requires-Dist: beautifulsoup4
Requires-Dist: chardet
Requires-Dist: dashtable
Requires-Dist: dateparser
Requires-Dist: mammoth
Requires-Dist: openpyxl
Requires-Dist: parse
Requires-Dist: Pillow
Requires-Dist: ply
Requires-Dist: pypandoc
Requires-Dist: pypdf
Requires-Dist: pyperclip
Requires-Dist: python-docx
Requires-Dist: python-pptx
Requires-Dist: python-telegram-bot
Requires-Dist: requests
Requires-Dist: toml
Requires-Dist: watchdog
Dynamic: author
Dynamic: author-email
Dynamic: classifier
Dynamic: description
Dynamic: description-content-type
Dynamic: home-page
Dynamic: license-file
Dynamic: requires-dist
Dynamic: summary
